LICENSE
MANIFEST.in
README.md
setup.cfg
setup.py
DavesLogger/Color.py
DavesLogger/Format.py
DavesLogger/Logger.py
DavesLogger/Logs.py
DavesLogger/Text.py
DavesLogger/__init__.py
DavesLogger.egg-info/PKG-INFO
DavesLogger.egg-info/SOURCES.txt
DavesLogger.egg-info/dependency_links.txt
DavesLogger.egg-info/requires.txt
DavesLogger.egg-info/top_level.txt