Metadata-Version: 2.1
Name: DavesLogger
Version: 1.1.0
Summary: Simple logger for Python
Home-page: https://github.com/Dmunch04/DavesLogger
Author: Munchii
Author-email: contact@munchii.me
License: MIT
Keywords: simple logger for python
Platform: UNKNOWN
Classifier: Development Status :: 4 - Beta
Classifier: Intended Audience :: End Users/Desktop
Classifier: Intended Audience :: Developers
Classifier: License :: OSI Approved :: MIT License
Classifier: Programming Language :: Python :: 2
Classifier: Programming Language :: Python :: 3
Classifier: Operating System :: OS Independent
